strip_spreadsheet.py
strip_spreadsheet-1.0.0.dist-info/LICENSE.txt
strip_spreadsheet-1.0.0.dist-info/METADATA
strip_spreadsheet-1.0.0.dist-info/WHEEL
strip_spreadsheet-1.0.0.dist-info/top_level.txt
strip_spreadsheet-1.0.0.dist-info/RECORD
