Metadata-Version: 2.1
Name: strip-spreadsheet
Version: 1.0.0
Summary: Strip a spreadsheet of extra spaces and blank-celled rows
Home-page: UNKNOWN
License: UNKNOWN
Platform: UNKNOWN
Classifier: Programming Language :: Python :: 3
Classifier: Programming Language :: Python :: 3.6
Classifier: Programming Language :: Python :: 3.7
Classifier: Programming Language :: Python :: 3.8
Classifier: Operating System :: OS Independent
